hirsch/__init__.py
hirsch/hirsch.py
hirsch-0.1.dist-info/METADATA
hirsch-0.1.dist-info/WHEEL
hirsch-0.1.dist-info/licenses/LICENSE
hirsch-0.1.dist-info/RECORD
