Metadata-Version: 2.3
Name: hirsch
Version: 0.1
Summary: Abstracted, continuous, and normalised of version of the Hirsch index (h-index) from academic writing for use as a statistical measure of even distribution
Project-URL: Homepage, https://github.com/mwinokan/Hirsch/issues
Project-URL: Bug Tracker, https://github.com/mwinokan/Hirsch/issues
Author-email: Max Winokan <max@winokan.com>
License-File: LICENSE
Classifier: License :: OSI Approved :: MIT License
Classifier: Operating System :: OS Independent
Classifier: Programming Language :: Python :: 3
Requires-Python: >=3.7
Requires-Dist: numpy
